README.md
setup.py
emergency_reporting/__init__.py
emergency_reporting/api.py
emergency_reporting/auth.py
emergency_reporting/client.py
emergency_reporting/excpetion.py
emergency_reporting/product.py
emergency_reporting/subscription.py
emergency_reporting/util.py
emergency_reporting.egg-info/PKG-INFO
emergency_reporting.egg-info/SOURCES.txt
emergency_reporting.egg-info/dependency_links.txt
emergency_reporting.egg-info/requires.txt
emergency_reporting.egg-info/top_level.txt